
[
  {
    "species": "Chromodoris willani",
    "nudi_link": "https://nudipixel.net/species/chromodoris_willani",
    "inaturalist_link": "https://www.inaturalist.org/taxa/119429-Chromodoris-willani",
    "seaslugforum_link": "http://www.seaslugforum.net/factsheet/chrowill",
    "worms_link": "https://www.marinespecies.org/aphia.php?p=taxdetails&id=558217",
    "wikipedia_link": "https://en.wikipedia.org/wiki/Chromodoris_willani"
  },
  {
    "species": "Berghia coerulescens",
    "nudi_link": "https://nudipixel.net/species/berghia_coerulescens",
    "inaturalist_link": "https://www.inaturalist.org/taxa/56645-Berghia-coerulescens",
    "seaslugforum_link": "http://www.seaslugforum.net/factsheet/bergcoer",
    "worms_link": "https://www.marinespecies.org/aphia.php?p=taxdetails&id=196603",
    "wikipedia_link": "https://en.wikipedia.org/wiki/Berghia_coerulescens"
  },
  {
    "species": "Costasiella kuroshimae",
    "nudi_link": "https://nudipixel.net/species/costasiella_kuroshimae",
    "inaturalist_link": "https://www.inaturalist.org/taxa/469221-Costasiella-kuroshimae",
    "seaslugforum_link": "http://www.seaslugforum.net/factsheet/costkuro",
    "worms_link": "https://www.marinespecies.org/aphia.php?p=taxdetails&id=494406",
    "wikipedia_link": "https://en.wikipedia.org/wiki/Costasiella_kuroshimae"
  },
  {
    "species": "Glaucus atlanticus",
    "nudi_link": "https://nudipixel.net/species/glaucus_atlanticus",
    "inaturalist_link": "https://www.inaturalist.org/taxa/50498-Glaucus-atlanticus",
    "seaslugforum_link": "http://www.seaslugforum.net/factsheet/glauatla",
    "worms_link": "https://www.marinespecies.org/aphia.php?p=taxdetails&id=181238",
    "wikipedia_link": "https://en.wikipedia.org/wiki/Glaucus_atlanticus"
  },
  {
    "species": "Phidiana militaris",
    "nudi_link": "https://nudipixel.net/species/caloria_militaris",
    "inaturalist_link": "https://www.inaturalist.org/taxa/50992-Phidiana-militaris",
    "seaslugforum_link": "http://www.seaslugforum.net/factsheet/phidmili",
    "worms_link": "https://www.marinespecies.org/aphia.php?p=taxdetails&id=404960",
    "wikipedia_link": "https://en.wikipedia.org/wiki/Phidiana_militaris"
  },
  {
    "species": "Felimare cantabrica",
    "nudi_link": "https://nudipixel.net/species/hypselodoris_cantabrica",
    "inaturalist_link": "https://www.inaturalist.org/taxa/469300-Felimare-cantabrica",
    "seaslugforum_link": "http://www.seaslugforum.net/factsheet/hypscant",
    "worms_link": "https://www.marinespecies.org/aphia.php?p=taxdetails&id=597543",
    "wikipedia_link": "https://en.wikipedia.org/wiki/Felimare_cantabrica"
  },
  {
    "species": "Nembrotha cristata",
    "nudi_link": "https://nudipixel.net/species/nembrotha_cristata",
    "inaturalist_link": "https://www.inaturalist.org/taxa/119438-Nembrotha-cristata",
    "seaslugforum_link": "http://www.seaslugforum.net/factsheet/nembcris",
    "worms_link": "https://www.marinespecies.org/aphia.php?p=taxdetails&id=527320",
    "wikipedia_link": "https://en.wikipedia.org/wiki/Nembrotha_cristata"
  },
  {
    "species": "Paraflabellina ischitana",
    "nudi_link": "https://nudipixel.net/species/flabellina_ischitana",
    "inaturalist_link": "https://www.inaturalist.org/taxa/326339-Paraflabellina-ischitana",
    "seaslugforum_link": "",
    "worms_link": "https://www.marinespecies.org/aphia.php?p=taxdetails&id=1037385",
    "wikipedia_link": "https://en.wikipedia.org/wiki/Paraflabellina_ischitana"
  },
  {
    "species": "Nembrotha kubaryana",
    "nudi_link": "https://nudipixel.net/species/nembrotha_kubaryana",
    "inaturalist_link": "https://www.inaturalist.org/taxa/126110-Nembrotha-kubaryana",
    "seaslugforum_link": "http://www.seaslugforum.net/factsheet/nembkuby",
    "worms_link": "https://www.marinespecies.org/aphia.php?p=taxdetails&id=527322",
    "wikipedia_link": "https://en.wikipedia.org/wiki/Nembrotha_kubaryana"
  },
  {
    "species": "Nembrotha purpureolineata",
    "nudi_link": "https://nudipixel.net/species/nembrotha_purpureolineata",
    "inaturalist_link": "https://www.inaturalist.org/taxa/194604-Nembrotha-purpureolineata",
    "seaslugforum_link": "http://www.seaslugforum.net/factsheet/nembpurp",
    "worms_link": "https://www.marinespecies.org/aphia.php?p=taxdetails&id=527330",
    "wikipedia_link": "https://en.wikipedia.org/wiki/Nembrotha_purpureolineata"
  },
  {
    "species": "Hypselodoris kanga",
    "nudi_link": "https://nudipixel.net/species/hypselodoris_kanga",
    "inaturalist_link": "https://www.inaturalist.org/taxa/473492-Hypselodoris-kanga",
    "seaslugforum_link": "http://www.seaslugforum.net/factsheet/hypskang",
    "worms_link": "https://www.marinespecies.org/aphia.php?p=taxdetails&id=209599",
    "wikipedia_link": "https://en.wikipedia.org/wiki/Hypselodoris_kanga"
  },
  {
    "species": "Nembrotha megalocera",
    "nudi_link": "https://nudipixel.net/species/nembrotha_megalocera",
    "inaturalist_link": "https://www.inaturalist.org/taxa/504152-Nembrotha-megalocera",
    "seaslugforum_link": "http://www.seaslugforum.net/factsheet/nembmega",
    "worms_link": "https://www.marinespecies.org/aphia.php?p=taxdetails&id=527327",
    "wikipedia_link": "https://en.wikipedia.org/wiki/Nembrotha_megalocera"
  },
  {
    "species": "Flabellina iodinea",
    "nudi_link": "https://nudipixel.net/species/flabellina_iodinea",
    "inaturalist_link": "https://www.inaturalist.org/taxa/47171-Flabellina-iodinea",
    "seaslugforum_link": "http://www.seaslugforum.net/factsheet/flabiodi",
    "worms_link": "https://www.marinespecies.org/aphia.php?p=taxdetails&id=1047483",
    "wikipedia_link": "https://en.wikipedia.org/wiki/Flabellina_iodinea"
  },
  {
    "species": "Goniobranchus kuniei",
    "nudi_link": "https://nudipixel.net/species/goniobranchus_kuniei",
    "inaturalist_link": "https://www.inaturalist.org/taxa/119439-Goniobranchus-kuniei",
    "seaslugforum_link": "http://www.seaslugforum.net/factsheet/chrokuni",
    "worms_link": "https://www.marinespecies.org/aphia.php?p=taxdetails&id=597339",
    "wikipedia_link": "https://en.wikipedia.org/wiki/Goniobranchus_kuniei"
  },
  {
    "species": "Chromodoris annae",
    "nudi_link": "https://nudipixel.net/species/chromodoris_annae",
    "inaturalist_link": "https://www.inaturalist.org/taxa/119434-Chromodoris-annae",
    "seaslugforum_link": "http://www.seaslugforum.net/factsheet/chroanna",
    "worms_link": "https://www.marinespecies.org/aphia.php?p=taxdetails&id=558229",
    "wikipedia_link": "https://en.wikipedia.org/wiki/Chromodoris_annae"
  },
  {
    "species": "Hexabranchus sanguineus",
    "nudi_link": "https://nudipixel.net/species/hexabranchus_sanguineus",
    "inaturalist_link": "https://www.inaturalist.org/taxa/244849-Hexabranchus-sanguineus",
    "seaslugforum_link": "http://www.seaslugforum.net/factsheet/hexasang",
    "worms_link": "https://www.marinespecies.org/aphia.php?p=taxdetails&id=220381",
    "wikipedia_link": "https://en.wikipedia.org/wiki/Hexabranchus_sanguineus"
  },
  {
    "species": "Phyllidia varicosa",
    "nudi_link": "https://nudipixel.net/species/phyllidia_varicosa",
    "inaturalist_link": "https://www.inaturalist.org/taxa/49735-Phyllidia-varicosa",
    "seaslugforum_link": "http://www.seaslugforum.net/factsheet/phyvari",
    "worms_link": "https://www.marinespecies.org/aphia.php?p=taxdetails&id=212835",
    "wikipedia_link": "https://en.wikipedia.org/wiki/Phyllidia_varicosa"
  },
  {
    "species": "Flabellina affinis",
    "nudi_link": "https://nudipixel.net/species/flabellina_affinis",
    "inaturalist_link": "https://www.inaturalist.org/taxa/326338-Flabellina-affinis",
    "seaslugforum_link": "http://www.seaslugforum.net/factsheet/flabaffi",
    "worms_link": "https://www.marinespecies.org/aphia.php?p=taxdetails&id=139988",
    "wikipedia_link": "https://en.wikipedia.org/wiki/Flabellina_affinis"
  }
  
  {
    "species": "Hypselodoris apolegma",
    "nudi_link": "https://nudipixel.net/species/hypselodoris_apolegma",
    "inaturalist_link": "https://www.inaturalist.org/taxa/54667-Hypselodoris-apolegma",
    "seaslugforum_link": "http://www.seaslugforum.net/factsheet/hypsapol",
    "worms_link": "https://www.marinespecies.org/aphia.php?p=taxdetails&id=560044",
    "wikipedia_link": "https://en.wikipedia.org/wiki/Hypselodoris_apolegma"
  },
  {
    "species": "Thecacera pacifica",
    "nudi_link": "https://nudipixel.net/species/thecacera_pacifica",
    "inaturalist_link": "https://www.inaturalist.org/taxa/142790-Thecacera-pacifica",
    "seaslugforum_link": "http://www.seaslugforum.net/factsheet/thecpaci",
    "worms_link": "https://www.marinespecies.org/aphia.php?p=taxdetails&id=420618",
    "wikipedia_link": "https://en.wikipedia.org/wiki/Thecacera_pacifica"
  },
  {
    "species": "Ceratosoma amoenum",
    "nudi_link": "https://nudipixel.net/species/ceratosoma_amoenum",
    "inaturalist_link": "https://www.inaturalist.org/taxa/418514-Ceratosoma-amoenum",
    "seaslugforum_link": "http://www.seaslugforum.net/factsheet/ceraamoe",
    "worms_link": "https://www.marinespecies.org/aphia.php?p=taxdetails&id=533898",
    "wikipedia_link": "https://en.wikipedia.org/wiki/Ceratosoma_amoenum"
  },
  {
    "species": "Hypselodoris tryoni",
    "nudi_link": "https://nudipixel.net/species/hypselodoris_tryoni",
    "inaturalist_link": "https://www.inaturalist.org/taxa/468033-Hypselodoris-tryoni",
    "seaslugforum_link": "http://www.seaslugforum.net/factsheet/hypstryo",
    "worms_link": "https://www.marinespecies.org/aphia.php?p=taxdetails&id=558646",
    "wikipedia_link": "https://en.wikipedia.org/wiki/Hypselodoris_tryoni"
  },
  {
    "species": "Hypselodoris variobranchia",
    "nudi_link": "https://nudipixel.net/species/hypselodoris_variobranchia",
    "inaturalist_link": "https://www.inaturalist.org/taxa/780919-Hypselodoris-variobranchia",
    "seaslugforum_link": "http://www.seaslugforum.net/factsheet/hypsvari",
    "worms_link": "https://www.marinespecies.org/aphia.php?p=taxdetails&id=1297853",
    "wikipedia_link": "https://en.wikipedia.org/wiki/Hypselodoris_variobranchia"
  },
  {
    "species": "Bornella anguilla",
    "nudi_link": "https://nudipixel.net/species/bornella_anguilla",
    "inaturalist_link": "https://www.inaturalist.org/taxa/64717-Bornella-anguilla",
    "seaslugforum_link": "http://www.seaslugforum.net/factsheet/bornangu",
    "worms_link": "https://www.marinespecies.org/aphia.php?p=taxdetails&id=494411",
    "wikipedia_link": "https://en.wikipedia.org/wiki/Bornella_anguilla"
  },
  {
    "species": "Phyllidia ocellata",
    "nudi_link": "https://nudipixel.net/species/phyllidia_ocellata",
    "inaturalist_link": "https://www.inaturalist.org/taxa/50554-Phyllidia-ocellata",
    "seaslugforum_link": "http://www.seaslugforum.net/factsheet/phylocel",
    "worms_link": "https://www.marinespecies.org/aphia.php?p=taxdetails&id=536661",
    "wikipedia_link": "https://en.wikipedia.org/wiki/Phyllidia_ocellata"
  },
  {
    "species": "Glossodoris cincta",
    "nudi_link": "https://nudipixel.net/species/glossodoris_cincta",
    "inaturalist_link": "https://www.inaturalist.org/taxa/126093-Glossodoris-cincta",
    "seaslugforum_link": "http://www.seaslugforum.net/factsheet/gloscinc",
    "worms_link": "https://www.marinespecies.org/aphia.php?p=taxdetails&id=220426",
    "wikipedia_link": "https://en.wikipedia.org/wiki/Glossodoris_cincta"
  },
  {
    "species": "Mexichromis macropus",
    "nudi_link": "https://nudipixel.net/species/mexichromis_macropus",
    "inaturalist_link": "https://www.inaturalist.org/taxa/418341-Mexichromis-macropus",
    "seaslugforum_link": "http://www.seaslugforum.net/factsheet/meximacr",
    "worms_link": "https://www.marinespecies.org/aphia.php?p=taxdetails&id=457360",
    "wikipedia_link": "https://en.wikipedia.org/wiki/Mexichromis_macropus"
  },
  {
    "species": "Aegires villosus",
    "nudi_link": "https://nudipixel.net/species/aegires_villosus",
    "inaturalist_link": "https://www.inaturalist.org/taxa/467975-Aegires-villosus",
    "seaslugforum_link": "http://www.seaslugforum.net/factsheet/aegivill",
    "worms_link": "https://www.marinespecies.org/aphia.php?p=taxdetails&id=196605",
    "wikipedia_link": "https://en.wikipedia.org/wiki/Aegires_villosus"
  },
  {
    "species": "Felimare picta",
    "nudi_link": "https://nudipixel.net/species/felimare_picta",
    "inaturalist_link": "https://www.inaturalist.org/taxa/469400-Felimare-picta",
    "seaslugforum_link": "http://www.seaslugforum.net/factsheet/felipict",
    "worms_link": "https://www.marinespecies.org/aphia.php?p=taxdetails&id=597536",
    "wikipedia_link": "https://en.wikipedia.org/wiki/Felimare_picta"
  },
  {
    "species": "Janolus savinkini",
    "nudi_link": "https://nudipixel.net/species/janolus_savinkini",
    "inaturalist_link": "https://www.inaturalist.org/taxa/497250-Janolus-savinkini",
    "seaslugforum_link": "http://www.seaslugforum.net/factsheet/janosavi",
    "worms_link": "https://www.marinespecies.org/aphia.php?p=taxdetails&id=723627",
    "wikipedia_link": "https://en.wikipedia.org/wiki/Janolus_savinkini"
  },
  {
    "species": "Goniobranchus geminus",
    "nudi_link": "https://nudipixel.net/species/goniobranchus_geminus",
    "inaturalist_link": "https://www.inaturalist.org/taxa/502350-Goniobranchus-geminus",
    "seaslugforum_link": "http://www.seaslugforum.net/factsheet/chrogemi",
    "worms_link": "https://www.marinespecies.org/aphia.php?p=taxdetails&id=209585",
    "wikipedia_link": "https://en.wikipedia.org/wiki/Goniobranchus_geminus"
  },
  {
    "species": "Polycera quadrilineata",
    "nudi_link": "https://nudipixel.net/species/polycera_quadrilineata",
    "inaturalist_link": "https://www.inaturalist.org/taxa/425249-Polycera-quadrilineata",
    "seaslugforum_link": "http://www.seaslugforum.net/factsheet/polyquad",
    "worms_link": "https://www.marinespecies.org/aphia.php?p=taxdetails&id=140835",
    "wikipedia_link": "https://en.wikipedia.org/wiki/Polycera_quadrilineata"
  },
  {
    "species": "Fjordia lineata",
    "nudi_link": "https://nudipixel.net/species/fjordia_lineata",
    "inaturalist_link": "https://www.inaturalist.org/taxa/606085-Fjordia-lineata",
    "seaslugforum_link": "http://www.seaslugforum.net/factsheet/fjorline",
    "worms_link": "https://www.marinespecies.org/aphia.php?p=taxdetails&id=1047516",
    "wikipedia_link": "https://en.wikipedia.org/wiki/Fjordia_lineata"
  },
  {
    "species": "Hermissenda crassicornis",
    "nudi_link": "https://nudipixel.net/species/hermissenda_crassicornis",
    "inaturalist_link": "https://www.inaturalist.org/taxa/47209-Hermissenda-crassicornis",
    "seaslugforum_link": "http://www.seaslugforum.net/factsheet/hermcras",
    "worms_link": "https://www.marinespecies.org/aphia.php?p=taxdetails&id=509936",
    "wikipedia_link": "https://en.wikipedia.org/wiki/Hermissenda_crassicornis"
  },
  {
    "species": "Ceratosoma tenue",
    "nudi_link": "https://nudipixel.net/species/ceratosoma_tenue",
    "inaturalist_link": "https://www.inaturalist.org/taxa/120937-Ceratosoma-tenue",
    "seaslugforum_link": "http://www.seaslugforum.net/factsheet/ceratenu",
    "worms_link": "https://www.marinespecies.org/aphia.php?p=taxdetails&id=212893",
    "wikipedia_link": "https://en.wikipedia.org/wiki/Ceratosoma_tenue"
  },
  {
    "species": "Felimare californiensis",
    "nudi_link": "https://nudipixel.net/species/felimare_californiensis/",
    "inaturalist_link": "https://www.inaturalist.org/taxa/469723-Felimare-californiensis",
    "seaslugforum_link": "http://www.seaslugforum.net/factsheet/hypscali",
    "worms_link": "https://www.marinespecies.org/aphia.php?p=taxdetails&id=597520",
    "wikipedia_link": "https://en.wikipedia.org/wiki/Felimare_californiensis"
  },
  {
    "species": "Tambja verconis",
    "nudi_link": "https://nudipixel.net/species/tambja_verconis/",
    "inaturalist_link": "https://www.inaturalist.org/taxa/397793-Tambja-verconis",
    "seaslugforum_link": "http://www.seaslugforum.net/factsheet/tambverc",
    "worms_link": "https://www.marinespecies.org/aphia.php?p=taxdetails&id=531168",
    "wikipedia_link": "https://en.wikipedia.org/wiki/Tambja_verconis"
  },
  {
    "species": "Hypselodoris decorata",
    "nudi_link": "https://nudipixel.net/species/hypselodoris_decorata/",
    "inaturalist_link": "https://www.inaturalist.org/taxa/782298-Hypselodoris-decorata",
    "seaslugforum_link": "http://www.seaslugforum.net/factsheet/hypsdeco",
    "worms_link": "https://www.marinespecies.org/aphia.php?p=taxdetails&id=565422",
    "wikipedia_link": "https://en.wikipedia.org/wiki/Hypselodoris_decorata"
  },
  {
    "species": "Hypselodoris infucata",
    "nudi_link": "https://nudipixel.net/species/hypselodoris_infucata/",
    "inaturalist_link": "https://www.inaturalist.org/taxa/52862-Hypselodoris-infucata",
    "seaslugforum_link": "http://www.seaslugforum.net/factsheet/hypsinfu",
    "worms_link": "https://www.marinespecies.org/aphia.php?p=taxdetails&id=139151",
    "wikipedia_link": "https://en.wikipedia.org/wiki/Hypselodoris_infucata"
  },
  {
    "species": "Tambja blacki",
    "nudi_link": "https://nudipixel.net/species/tambja_blacki/",
    "inaturalist_link": "https://www.inaturalist.org/taxa/628397-Tambja-blacki",
    "seaslugforum_link": "",
    "worms_link": "https://www.marinespecies.org/aphia.php?p=taxdetails&id=389899",
    "wikipedia_link": "https://en.wikipedia.org/wiki/Tambja_blacki"
  },
  {
    "species": "Hypselodoris obscura",
    "nudi_link": "https://nudipixel.net/species/hypselodoris_obscura/",
    "inaturalist_link": "https://www.inaturalist.org/taxa/129108-Hypselodoris-obscura",
    "seaslugforum_link": "http://www.seaslugforum.net/factsheet/hypsobsc",
    "worms_link": "https://www.marinespecies.org/aphia.php?p=taxdetails&id=558622",
    "wikipedia_link": ""
  },
  {
    "species": "Chromodoris magnifica",
    "nudi_link": "https://nudipixel.net/species/chromodoris_magnifica/",
    "inaturalist_link": "https://www.inaturalist.org/taxa/121048-Chromodoris-magnifica",
    "seaslugforum_link": "",
    "worms_link": "https://www.marinespecies.org/aphia.php?p=taxdetails&id=558230",
    "wikipedia_link": ""
  },
  {
    "species": "Caloria militaris",
    "nudi_link": "https://nudipixel.net/species/caloria_militaris/",
    "inaturalist_link": "https://www.inaturalist.org/taxa/50992-Phidiana-militaris",
    "seaslugforum_link": "",
    "worms_link": "https://www.marinespecies.org/aphia.php?p=taxdetails&id=872548",
    "wikipedia_link": "https://en.wikipedia.org/wiki/Phidiana_militaris"
  },
  {
    "species": "Chelidonura mandroroa",
    "nudi_link": "https://nudipixel.net/species/chelidonura_mandroroa/",
    "inaturalist_link": "https://www.inaturalist.org/taxa/803531-Mariaglaja-mandroroa",
    "seaslugforum_link": "",
    "worms_link": "https://www.marinespecies.org/aphia.php?p=taxdetails&id=559042",
    "wikipedia_link": ""
  },
  {
    "species": "Goniobranchus vibratus",
    "nudi_link": "https://nudipixel.net/species/goniobranchus_vibratus/",
    "inaturalist_link": "https://www.inaturalist.org/taxa/597345-Goniobranchus-vibratus",
    "seaslugforum_link": "",
    "worms_link": "https://www.marinespecies.org/aphia.php?p=taxdetails&id=597345",
    "wikipedia_link": "https://en.wikipedia.org/wiki/Goniobranchus_vibratus"
  },
  {
    "species": "Goniobranchus coi",
    "nudi_link": "https://nudipixel.net/species/goniobranchus_coi/",
    "inaturalist_link": "https://www.inaturalist.org/taxa/597329-Goniobranchus-coi",
    "seaslugforum_link": "",
    "worms_link": "https://www.marinespecies.org/aphia.php?p=taxdetails&id=597329",
    "wikipedia_link": ""
  },
  {
    "species": "Tambja sagamiana",
    "nudi_link": "https://nudipixel.net/species/tambja_sagamiana/",
    "inaturalist_link": "https://www.inaturalist.org/taxa/871920-Tambja-sagamiana",
    "seaslugforum_link": "",
    "worms_link": "https://www.marinespecies.org/aphia.php?p=taxdetails&id=531186",
    "wikipedia_link": ""
  },
  {
    "species": "Hypselodoris kaname",
    "nudi_link": "https://nudipixel.net/species/hypselodoris_kaname/",
    "inaturalist_link": "",
    "seaslugforum_link": "",
    "worms_link": "https://www.marinespecies.org/aphia.php?p=taxdetails&id=560040",
    "wikipedia_link": ""
  },
  {
    "species": "Hypselodoris nigrostriata",
    "nudi_link": "https://nudipixel.net/species/hypselodoris_nigrostriata/",
    "inaturalist_link": "",
    "seaslugforum_link": "",
    "worms_link": "https://www.marinespecies.org/aphia.php?p=taxdetails&id=209600",
    "wikipedia_link": ""
  },
  {
    "species": "Hypselodoris krakatoa",
    "nudi_link": "https://nudipixel.net/species/hypselodoris_krakatoa/",
    "inaturalist_link": "",
    "seaslugforum_link": "",
    "worms_link": "https://www.marinespecies.org/aphia.php?p=taxdetails&id=457526",
    "wikipedia_link": "https://en.wikipedia.org/wiki/Hypselodoris_krakatoa"
  },
  {
    "species": "Goniobranchus leopardus",
    "nudi_link": "https://nudipixel.net/species/goniobranchus_leopardus/",
    "inaturalist_link": "",
    "seaslugforum_link": "",
    "worms_link": "https://www.marinespecies.org/aphia.php?p=taxdetails&id=833143",
    "wikipedia_link": ""
  },
  {
    "species": "Goniobranchus fidelis",
    "nudi_link": "https://nudipixel.net/species/goniobranchus_fidelis/",
    "inaturalist_link": "https://www.inaturalist.org/taxa/597334-Goniobranchus-fidelis",
    "seaslugforum_link": "",
    "worms_link": "https://www.marinespecies.org/aphia.php?p=taxdetails&id=597334",
    "wikipedia_link": "https://en.wikipedia.org/wiki/Goniobranchus_fidelis"
  }
]

